picture_service_proto/__init__.py
picture_service_proto/client_pb2.py
picture_service_proto/client_pb2.pyi
picture_service_proto/client_pb2_grpc.py
picture_service_proto/py.typed
picture_service_proto-2.0.0.dist-info/METADATA
picture_service_proto-2.0.0.dist-info/WHEEL
picture_service_proto-2.0.0.dist-info/top_level.txt
picture_service_proto-2.0.0.dist-info/RECORD
